INSTALL.rst
LICENSE
MANIFEST.in
README.rst
requirements.txt
setup.cfg
setup.py
src/ej_conversations/__init__.py
src/ej_conversations/admin.py
src/ej_conversations/api.py
src/ej_conversations/apps.py
src/ej_conversations/config.py
src/ej_conversations/fields.py
src/ej_conversations/forms.py
src/ej_conversations/mixins.py
src/ej_conversations/mommy_recipes.py
src/ej_conversations/permissions.py
src/ej_conversations/serializers.py
src/ej_conversations/utils.py
src/ej_conversations/validators.py
src/ej_conversations/viewsets.py
src/ej_conversations.egg-info/PKG-INFO
src/ej_conversations.egg-info/SOURCES.txt
src/ej_conversations.egg-info/dependency_links.txt
src/ej_conversations.egg-info/not-zip-safe
src/ej_conversations.egg-info/requires.txt
src/ej_conversations.egg-info/top_level.txt
src/ej_conversations/migrations/0001_initial.py
src/ej_conversations/migrations/__init__.py
src/ej_conversations/models/__init__.py
src/ej_conversations/models/category.py
src/ej_conversations/models/comment.py
src/ej_conversations/models/conversation.py
src/ej_conversations/models/conversation_extra.py
src/ej_conversations/models/limits.py
src/ej_conversations/models/managers.py
src/ej_conversations/models/stereotype.py
src/ej_conversations/models/vote.py