Metadata-Version: 2.1
Name: ej-conversations
Version: 0.1.0b0
Summary: Conversations, comments and votes for EJ platform.
Home-page: https://github.com/ejplatform/ej-conversations
Author: Fábio Macêdo Mendes
Author-email: fabiomacedomendes@gmail.com
License: GNU General Public License (GPL)
Keywords: web development,participation
Platform: UNKNOWN
Classifier: Development Status :: 4 - Beta
Classifier: Intended Audience :: Developers
Classifier: Operating System :: POSIX
Classifier: Programming Language :: Python
Classifier: Programming Language :: Python :: 3
Classifier: Programming Language :: Python :: 3.6
Classifier: Programming Language :: Python :: 3.7
Classifier: Topic :: Software Development :: Libraries
Classifier: Framework :: Django :: 1.11
Classifier: Framework :: Django :: 2.0
Provides-Extra: docs
Provides-Extra: dev
